z3c/ptcompat/__init__.py
z3c/ptcompat/configure.zcml
z3c/ptcompat/engine.py
z3c/ptcompat/tests.py
z3c_ptcompat-5.0.dist-info/LICENSE.txt
z3c_ptcompat-5.0.dist-info/METADATA
z3c_ptcompat-5.0.dist-info/WHEEL
z3c_ptcompat-5.0.dist-info/top_level.txt
z3c_ptcompat-5.0.dist-info/RECORD
