Metadata-Version: 2.2
Name: z3c.ptcompat
Version: 5.0
Summary: Zope-compatible page template engine based on Chameleon.
Home-page: https://github.com/zopefoundation/z3c.ptcompat
Author: Zope Foundation and Contributors
Author-email: zope-dev@zope.dev
License: ZPL
Project-URL: Issue Tracker, https://github.com/zopefoundation/z3c.ptcompat/issues
Project-URL: Sources, https://github.com/zopefoundation/z3c.ptcompat
Keywords: zpt template zope
Classifier: Development Status :: 5 - Production/Stable
Classifier: Environment :: Web Environment
Classifier: Intended Audience :: Developers
Classifier: License :: OSI Approved :: Zope Public License
Classifier: Programming Language :: Python
Classifier: Programming Language :: Python :: 3
Classifier: Programming Language :: Python :: 3.9
Classifier: Programming Language :: Python :: 3.10
Classifier: Programming Language :: Python :: 3.11
Classifier: Programming Language :: Python :: 3.12
Classifier: Programming Language :: Python :: 3.13
Classifier: Programming Language :: Python :: Implementation :: CPython
Classifier: Programming Language :: Python :: Implementation :: PyPy
Classifier: Natural Language :: English
Classifier: Operating System :: OS Independent
Classifier: Topic :: Software Development :: Libraries :: Python Modules
Classifier: Framework :: Plone
Classifier: Framework :: Zope :: 3
Classifier: Framework :: Zope :: 5
Requires-Python: >=3.9
License-File: LICENSE.txt
Requires-Dist: setuptools
Requires-Dist: z3c.pt>=3.0.0a1
Requires-Dist: zope.pagetemplate>=3.6.2
Requires-Dist: zope.traversing
Provides-Extra: test
Requires-Dist: zope.configuration; extra == "test"
Requires-Dist: zope.testing; extra == "test"
Requires-Dist: zope.testrunner>=6.4; extra == "test"
Dynamic: author
Dynamic: author-email
Dynamic: classifier
Dynamic: description
Dynamic: home-page
Dynamic: keywords
Dynamic: license
Dynamic: project-url
Dynamic: provides-extra
Dynamic: requires-dist
Dynamic: requires-python
Dynamic: summary
